geek/__init__.py
geek/characters/marvel.txt
geek/console.py
geek/generators.py
geek/providers.py
geek/utils.py
geek-0.1.1.dist-info/entry_points.txt
geek-0.1.1.dist-info/WHEEL
geek-0.1.1.dist-info/METADATA
geek-0.1.1.dist-info/RECORD
