Metadata-Version: 2.1
Name: geek
Version: 0.1.1
Summary: 
License: MIT
Author: Vlad Dmitrievich
Author-email: me@2tunnels.com
Requires-Python: >=3.8,<4.0
Classifier: License :: OSI Approved :: MIT License
Classifier: Programming Language :: Python :: 3
Classifier: Programming Language :: Python :: 3.8
Requires-Dist: python-slugify (>=4.0.0,<5.0.0)
